servicex_databinder/__init__.py
servicex_databinder/configuration.py
servicex_databinder/get_servicex_data.py
servicex_databinder/old_frontend.py
servicex_databinder/old_output.py
servicex_databinder/output_handler.py
servicex_databinder/request.py
servicex_databinder/servicex_databinder.py
servicex_databinder-0.5.0.dist-info/LICENSE
servicex_databinder-0.5.0.dist-info/METADATA
servicex_databinder-0.5.0.dist-info/WHEEL
servicex_databinder-0.5.0.dist-info/top_level.txt
servicex_databinder-0.5.0.dist-info/RECORD
