Metadata-Version: 2.1
Name: servicex-databinder
Version: 0.5.0
Summary: ServiceX data management                     using a configuration file
Home-page: https://github.com/kyungeonchoi/ServiceXDataBinder
Author: KyungEon Choi (UT Austin)
Author-email: kyungeonchoi@utexas.edu
License: BSD 3-clause
Platform: Any
Classifier: Development Status :: 3 - Alpha
Classifier: Intended Audience :: Developers
Classifier: Intended Audience :: Information Technology
Classifier: Intended Audience :: Science/Research
Classifier: Programming Language :: Python
Classifier: Topic :: Scientific/Engineering :: Physics
Classifier: Topic :: Software Development
Classifier: Topic :: Utilities
Requires-Python: >=3.7
License-File: LICENSE
Requires-Dist: servicex (>=2.6.2)
Requires-Dist: tcut-to-qastle (>=0.7)
Requires-Dist: nest-asyncio (>=1.5.1)
Requires-Dist: tqdm (>=4.60.0)
Requires-Dist: pyarrow (>=3.0.0)
Requires-Dist: backoff (>=1.11.1)
Requires-Dist: func-adl-servicex (>=2.2)
